{
    "version": "0.1.3",
    "architecture": {
        "32bit": {
            "url": "https://github.com/dustinblackman/gomodrun/releases/download/v0.1.3/gomodrun_0.1.3_windows_386.zip",
            "bin": [
                "gomodrun.exe"
            ],
            "hash": "b50f2c65fcd26f30b989b2556420f5dba1a1d8ce75f547402270a1a064460868"
        },
        "64bit": {
            "url": "https://github.com/dustinblackman/gomodrun/releases/download/v0.1.3/gomodrun_0.1.3_windows_amd64.zip",
            "bin": [
                "gomodrun.exe"
            ],
            "hash": "9e15f0f54f76adc60294a7e6fa81cb16403716bb55a908ee46cd3d04ad45c7b6"
        }
    },
    "homepage": "https://github.com/dustinblackman/gomodrun",
    "license": "MIT",
    "description": "The forgotten go tool that executes and caches binaries included in go.mod files"
}